jutge/heartbeat/heartbeat.py
jutge/heartbeat/listener.py
jutge_heartbeat-1.2.0.dist-info/LICENSE
jutge_heartbeat-1.2.0.dist-info/METADATA
jutge_heartbeat-1.2.0.dist-info/WHEEL
jutge_heartbeat-1.2.0.dist-info/entry_points.txt
jutge_heartbeat-1.2.0.dist-info/top_level.txt
jutge_heartbeat-1.2.0.dist-info/RECORD
