Metadata-Version: 2.1
Name: jutge-heartbeat
Version: 1.2.0
Summary: Heartbeat for worker machines of Jutge.org
Home-page: https://github.com/jutge-org/jutge-heartbeat
Author: Jordi Petit et al
Author-email: jpetit@cs.upc.edu
License: Apache
Download-URL: https://github.com/jutge-org/jutge-heartbeat/tarball/1.2.0
Keywords: jutge,jutge.org,heartbeat
Platform: UNKNOWN
Classifier: Development Status :: 5 - Production/Stable
Classifier: Environment :: Console
Classifier: Intended Audience :: Education
Classifier: License :: OSI Approved :: Apache Software License
Classifier: Operating System :: OS Independent
Classifier: Programming Language :: Python
Classifier: Programming Language :: Python :: 3
Classifier: Programming Language :: Python :: 3.5
Classifier: Programming Language :: Python :: 3.6
Classifier: Programming Language :: Python :: 3.7
Classifier: Topic :: Education
Requires-Dist: requests
Requires-Dist: jutge-monitor
